{
    "category_id": "251C13089",
    "category_name": "Хлеб, лаваш",
    "products_list": [
        {
            "product_info": {
                "plu": 3668480,
                "name": "Хлеб Schar Pan blanco без глютена нарезка 250г",
                "property": "250 г"
            }
        },
        {
            "product_info": {
                "plu": 3668482,
                "name": "Хлеб Dr. Schar Pan Rustico злаковый 250г",
                "property": "250 г"
            }
        },
        {
            "product_info": {
                "plu": 3668481,
                "name": "Хлеб Schar Pan Multigrano без глютена нарезка 250г",
                "property": "250 г"
            }
        },
        {
            "product_info": {
                "plu": 4096013,
                "name": "Лаваш Mission деревенский 3шт 270г",
                "property": "270 г"
            }
        },
        {
            "product_info": {
                "plu": 4256835,
                "name": "Булочка Bagerstat для бургера с кунжутом 3х56г",
                "property": "168 г"
            }
        },
        {
            "product_info": {
                "plu": 2039589,
                "name": "Лепешки Delicados Tortillas мексиканские 400г",
                "property": "400 г"
            }
        },
        {
            "product_info": {
                "plu": 4256836,
                "name": "Булочка Bagerstat для хот-дога 4х60г",
                "property": "241 г"
            }
        },
        {
            "product_info": {
                "plu": 2039592,
                "name": "Лепешка пшеничная Delicados тортилья мексиканская сырная 400г",
                "property": "400 г"
            }
        },
        {
            "product_info": {
                "plu": 3498077,
                "name": "Хлеб Черемушки Зерновик нарезка 460г",
                "property": "460 г"
            }
        },
        {
            "product_info": {
                "plu": 4331656,
                "name": "Лепешки Mission Тортильи со вкусом сыра 250г",
                "property": "250 г"
            }
        },
        {
            "product_info": {
                "plu": 2061861,
                "name": "Хлеб сандвичный Harry's American Sandwich пшеничный нарезка 470г",
                "property": "470 г"
            }
        },
        {
            "product_info": {
                "plu": 3439566,
                "name": "Лепешки Mission пшеничные оригинальные 250г",
                "property": "250 г"
            }
        },
        {
            "product_info": {
                "plu": 2065120,
                "name": "Батон Коломенское Нарезной нарезка 400г",
                "property": "400 г"
            }
        },
        {
            "product_info": {
                "plu": 4137972,
                "name": "Булочка для гамбургеров Bimbo с кунжутом 240г",
                "property": "240 г"
            }
        },
        {
            "product_info": {
                "plu": 2061863,
                "name": "Хлеб сандвичный Harry's American Sandwich пшеничный с отрубями нарезка 515 г",
                "property": "515 г"
            }
        },
        {
            "product_info": {
                "plu": 4370804,
                "name": "Булочки Коломенский пшеничные с кунжутом 3х60г",
                "property": "180 г"
            }
        },
        {
            "product_info": {
                "plu": 4018850,
                "name": "Хлеб Хлебозавод 28 Для Фитнеса нарезка 300г",
                "property": "300 г"
            }
        },
        {
            "product_info": {
                "plu": 3455615,
                "name": "Хлеб Ржаной Край зерновой нарезка 300г",
                "property": "300 г"
            }
        },
        {
            "product_info": {
                "plu": 3455614,
                "name": "Хлеб Ржаной Край заварной нарезка 300г",
                "property": "300 г"
            }
        },
        {
            "product_info": {
                "plu": 4153444,
                "name": "Булочка Бимбо Макси с кунжутом 252г",
                "property": "252 г"
            }
        },
        {
            "product_info": {
                "plu": 3476555,
                "name": "Хлебец Энергия здоровья Подовый с зернами и семенами нарезка 300г",
                "property": "300 г"
            }
        },
        {
            "product_info": {
                "plu": 3353197,
                "name": "Батон Хлебный Дом Утренний нарезка 400г",
                "property": "400 г"
            }
        },
        {
            "product_info": {
                "plu": 4361612,
                "name": "Хлеб Маркет Collection Ржевский цельнозерновой 450г",
                "property": "450 г"
            }
        },
        {
            "product_info": {
                "plu": 3643557,
                "name": "Хлебцы Коломенское зерновые 260г",
                "property": "260 г"
            }
        },
        {
            "product_info": {
                "plu": 3696941,
                "name": "Хлеб Коломенское Даниловский зерновой 300г",
                "property": "300 г"
            }
        },
        {
            "product_info": {
                "plu": 3682239,
                "name": "Хлеб Рижский хлеб Юбилейный бездрожжевой 205г",
                "property": "205 г"
            }
        },
        {
            "product_info": {
                "plu": 3693421,
                "name": "Лепешки Mission пшеничные тортильи гриль 250г",
                "property": "250 г"
            }
        },
        {
            "product_info": {
                "plu": 2059535,
                "name": "Хлеб Хлебный Дом Геркулес зерновой нарезка 500г",
                "property": "500 г"
            }
        },
        {
            "product_info": {
                "plu": 3620591,
                "name": "Лаваш Хлебное местечко элитный тандырный бездрожжевой 360г",
                "property": "360 г"
            }
        },
        {
            "product_info": {
                "plu": 4291806,
                "name": "Хлеб Спортхлеб цельнозерновой 450г",
                "property": "450 г"
            }
        },
        {
            "product_info": {
                "plu": 4103219,
                "name": "Хлеб Сибирский пекарь зерновой мультизлаковый со льном нарезка 280г",
                "property": "280 г"
            }
        },
        {
            "product_info": {
                "plu": 4361611,
                "name": "Хлеб Маркет Collection Пумперникель Вестфальский цельнозерновой 450г",
                "property": "450 г"
            }
        },
        {
            "product_info": {
                "plu": 3372334,
                "name": "Хлеб Хлебный Дом Марьин заварной 350г",
                "property": "350 г"
            }
        },
        {
            "product_info": {
                "plu": 4318510,
                "name": "Батон Маркет Горчичный нарезка 190г",
                "property": "190 г"
            }
        },
        {
            "product_info": {
                "plu": 4208524,
                "name": "Хлеб Коломенское Ржаной край цельнозерновой нарезка 300г",
                "property": "300 г"
            }
        },
        {
            "product_info": {
                "plu": 3424506,
                "name": "Хлеб Хлебный Дом Геркулес зерновой нарезка 250г",
                "property": "250 г"
            }
        },
        {
            "product_info": {
                "plu": 4296082,
                "name": "Лаваш Рижский хлеб из пшеничной муки 200г",
                "property": "200 г"
            }
        },
        {
            "product_info": {
                "plu": 2149541,
                "name": "Хлеб Черемушки Бородинский нарезка 390г",
                "property": "390 г"
            }
        },
        {
            "product_info": {
                "plu": 4001715,
                "name": "Хлеб Самарский пекарь ржаной зерновой нарезка 350г",
                "property": "350 г"
            }
        },
        {
            "product_info": {
                "plu": 3506194,
                "name": "Батон Черемушки Полюшко нарезка 300г",
                "property": "300 г"
            }
        },
        {
            "product_info": {
                "plu": 4287370,
                "name": "Хлебец Хлебный дом Стройный рецепт без дрожжей нарезка 350г",
                "property": "350 г"
            }
        },
        {
            "product_info": {
                "plu": 4138140,
                "name": "Хлеб Рижский хлеб ржаной со злаками 300г",
                "property": "300 г"
            }
        },
        {
            "product_info": {
                "plu": 4276930,
                "name": "Хлеб Коломенский Даниловский ржано-пшеничный нарезка 350г",
                "property": "350 г"
            }
        },
        {
            "product_info": {
                "plu": 3633467,
                "name": "Хлеб Рижский хлеб Цельнозерновой ржано-пшеничный 300г",
                "property": "300 г"
            }
        },
        {
            "product_info": {
                "plu": 3484089,
                "name": "Хлеб Рижский хлеб Ароматный подовый 300г",
                "property": "300 г"
            }
        },
        {
            "product_info": {
                "plu": 4050647,
                "name": "Хлеб Хлебный Дом тостовый пшеничный 350г",
                "property": "350 г"
            }
        },
        {
            "product_info": {
                "plu": 2149542,
                "name": "Батон Черемушки нарезка 400г",
                "property": "400 г"
            }
        },
        {
            "product_info": {
                "plu": 3631465,
                "name": "Хлеб Рижский Хлеб Ржаной 220г",
                "property": "220 г"
            }
        },
        {
            "product_info": {
                "plu": 2065124,
                "name": "Хлеб Коломенское Бородинский нарезка 400г",
                "property": "400 г"
            }
        },
        {
            "product_info": {
                "plu": 4049144,
                "name": "Хлеб Черемушки Столичный нарезка 330г",
                "property": "330 г"
            }
        },
        {
            "product_info": {
                "plu": 3497959,
                "name": "Лаваш тонкий Коломенское армянский 360г",
                "property": "360 г"
            }
        },
        {
            "product_info": {
                "plu": 3484091,
                "name": "Хлеб Рижский Хлеб Бородинский 300г",
                "property": "300 г"
            }
        },
        {
            "product_info": {
                "plu": 2065127,
                "name": "Батон Коломенское с отрубями 300г",
                "property": "300 г"
            }
        },
        {
            "product_info": {
                "plu": 3985404,
                "name": "Батон Хлебный Дом Звездный нарезка 350г",
                "property": "350 г"
            }
        },
        {
            "product_info": {
                "plu": 3953836,
                "name": "Хлеб Коломенское Дарницкий формовой нарезка 350г",
                "property": "350 г"
            }
        },
        {
            "product_info": {
                "plu": 3961492,
                "name": "Хлеб Хлебный Дом Геркулес с кукурузой нарезка 255г",
                "property": "255 г"
            }
        },
        {
            "product_info": {
                "plu": 4332762,
                "name": "Хлеб Коломенский Даниловский часть изделия нарезка 250г",
                "property": "250 г"
            }
        },
        {
            "product_info": {
                "plu": 3266204,
                "name": "Хлеб Хлебный Дом Геркулес с отрубями нарезка 250г",
                "property": "250 г"
            }
        },
        {
            "product_info": {
                "plu": 4050775,
                "name": "Хлеб Коломенское тостовый злаковый нарезка 250г",
                "property": "250 г"
            }
        },
        {
            "product_info": {
                "plu": 3357380,
                "name": "Хлеб Рижский хлеб Крестьянский бездрожжевой заварной подовый 300г",
                "property": "300 г"
            }
        },
        {
            "product_info": {
                "plu": 3940608,
                "name": "Лаваш Рижский Хлеб мини из пшеничной муки Мини, 200г",
                "property": "200 г"
            }
        },
        {
            "product_info": {
                "plu": 4094188,
                "name": "Хлеб Хлебное Местечко Курземский бездрожжевой 270г",
                "property": "270 г"
            }
        },
        {
            "product_info": {
                "plu": 3442368,
                "name": "Лаваш Нижегородский Хлеб армянский премиум 360г",
                "property": "360 г"
            }
        },
        {
            "product_info": {
                "plu": 3219554,
                "name": "Хлеб Селяночка Бородинский нарезка половина 350г",
                "property": "350 г"
            }
        },
        {
            "product_info": {
                "plu": 3696989,
                "name": "Батон Черемушки Нарезной нарезка 200г",
                "property": "200 г"
            }
        },
        {
            "product_info": {
                "plu": 4010437,
                "name": "Хлеб Черемушки Московский 340г",
                "property": "340 г"
            }
        },
        {
            "product_info": {
                "plu": 31014,
                "name": "Батон Щелковохлеб Щелковский нарезка 380г",
                "property": "380 г"
            }
        },
        {
            "product_info": {
                "plu": 53610,
                "name": "Хлеб Щелковохлеб Экстра нарезка 450г",
                "property": "450 г"
            }
        },
        {
            "product_info": {
                "plu": 4109830,
                "name": "Хлеб Зерница ржано-пшеничный бездрожжевой нарезка 300г",
                "property": "300 г"
            }
        },
        {
            "product_info": {
                "plu": 4245443,
                "name": "Хлеб Хлебное местечко бездрожжевой с семечками и медом 300г",
                "property": "300 г"
            }
        },
        {
            "product_info": {
                "plu": 4327015,
                "name": "Лаваш Нижегородский хлеб Премиум армянский нарезанный 8х25г",
                "property": "200 г"
            }
        },
        {
            "product_info": {
                "plu": 4298846,
                "name": "Хлеб Черемушки Кукурузный нарезка 300г",
                "property": "300 г"
            }
        },
        {
            "product_info": {
                "plu": 4318513,
                "name": "Хлеб Маркет Измайловский подовый нарезанный 360г",
                "property": "360 г"
            }
        },
        {
            "product_info": {
                "plu": 4315652,
                "name": "Хлеб Щелковохлеб Тостовый молочный нарезка 240г",
                "property": "240 г"
            }
        },
        {
            "product_info": {
                "plu": 3994705,
                "name": "Хлеб Рижский хлеб Ароматный ржано-пшеничный подовый с изюмом 300г",
                "property": "300 г"
            }
        },
        {
            "product_info": {
                "plu": 4193036,
                "name": "Хлебец Каравай наливной Черный Янтарь зерно и солод 300г",
                "property": "300 г"
            }
        },
        {
            "product_info": {
                "plu": 4059494,
                "name": "Хлеб Черемушки Бездрожжевой нарезка 320г",
                "property": "320 г"
            }
        },
        {
            "product_info": {
                "plu": 3634576,
                "name": "Хлеб Щелковохлеб Столичный нарезка 320г",
                "property": "320 г"
            }
        },
        {
            "product_info": {
                "plu": 36560,
                "name": "Лепешки Хлебный Дом Краюшки ржано-пшеничные 2х120г",
                "property": "240 г"
            }
        },
        {
            "product_info": {
                "plu": 3219528,
                "name": "Батон Селяночка Нарезной нарезка 400г",
                "property": "400 г"
            }
        },
        {
            "product_info": {
                "plu": 3284334,
                "name": "Хлеб Щелковохлеб тостовый нарезка 240г",
                "property": "240 г"
            }
        },
        {
            "product_info": {
                "plu": 4137632,
                "name": "Хлеб Рижский хлеб Крестьянский со злаками 300г",
                "property": "300 г"
            }
        },
        {
            "product_info": {
                "plu": 3442335,
                "name": "Хлеб Нижегородский Хлеб 400г",
                "property": "400 г"
            }
        },
        {
            "product_info": {
                "plu": 4090297,
                "name": "Хлеб Зерница Полезные рецепты Пшеничный злаковый нарезанный 300г",
                "property": "300 г"
            }
        },
        {
            "product_info": {
                "plu": 4001717,
                "name": "Хлеб Самарский Пекарь Четыре злака зерновой нарезка 350г",
                "property": "350 г"
            }
        },
        {
            "product_info": {
                "plu": 3404094,
                "name": "Хлеб Селяночка Дарницкий 320г",
                "property": "320 г"
            }
        },
        {
            "product_info": {
                "plu": 3357346,
                "name": "Булочка Щелковохлеб для хот-дога 4х75г",
                "property": "300 г"
            }
        },
        {
            "product_info": {
                "plu": 4116756,
                "name": "Лаваш Черемушки по-деревенски 160г",
                "property": "160 г"
            }
        },
        {
            "product_info": {
                "plu": 3911583,
                "name": "Хлеб Коломенское пшеничный тостовый 320г",
                "property": "320 г"
            }
        },
        {
            "product_info": {
                "plu": 4377679,
                "name": "Хлеб ЩелковоХлеб Зерновой Первохлеб нарезка 0.31кг",
                "property": "310 г"
            }
        },
        {
            "product_info": {
                "plu": 4238111,
                "name": "Лепешка Восточная сырная 300г",
                "property": "300 г"
            }
        },
        {
            "product_info": {
                "plu": 4096143,
                "name": "Батон Селяночка нарезной 200г",
                "property": "200 г"
            }
        },
        {
            "product_info": {
                "plu": 2053660,
                "name": "Хлеб Щелковохлеб Дарницкий в нарезке 320г",
                "property": "320 г"
            }
        },
        {
            "product_info": {
                "plu": 3427407,
                "name": "Хлеб Рижский Хлеб Деревенский бездрожжевой 220г",
                "property": "220 г"
            }
        },
        {
            "product_info": {
                "plu": 4129288,
                "name": "Хлеб Жуковский хлеб бездрожжевой 350г",
                "property": "350 г"
            }
        },
        {
            "product_info": {
                "plu": 3404092,
                "name": "Хлеб Селяночка Столичный подовый нарезка 320г",
                "property": "320 г"
            }
        },
        {
            "product_info": {
                "plu": 4157549,
                "name": "Хлеб Sibirien korn Brot зерновой 6 злаков с полбой нарезка 280г",
                "property": "280 г"
            }
        },
        {
            "product_info": {
                "plu": 76186,
                "name": "Хлеб Щелковохлеб Ржевский нарезка 700г",
                "property": "700 г"
            }
        },
        {
            "product_info": {
                "plu": 4292667,
                "name": "Хлеб Толга Симеоновский ржаной нарезанный 250г",
                "property": "250 г"
            }
        },
        {
            "product_info": {
                "plu": 31013,
                "name": "Батон Щелковохлеб Щелковский 380г",
                "property": "380 г"
            }
        },
        {
            "product_info": {
                "plu": 3419007,
                "name": "Хлеб Хлебное Местечко Митава бездрожжевой заварной нарезка, 300г",
                "property": "300 г"
            }
        },
        {
            "product_info": {
                "plu": 4349103,
                "name": "Хлеб Каравай Тихвинский подовый нарезка 300г",
                "property": "300 г"
            }
        },
        {
            "product_info": {
                "plu": 36573,
                "name": "Хлеб Хлебный Дом тостовый нарезка 500г",
                "property": "500 г"
            }
        },
        {
            "product_info": {
                "plu": 4305379,
                "name": "Хлеб Рижский Хлеб Веган из ржаной муки с зеленой гречкой и семенами тыквы 300г",
                "property": "300 г"
            }
        },
        {
            "product_info": {
                "plu": 3496198,
                "name": "Булочка Щелковохлеб для гамбургера 4х60г",
                "property": "240 г"
            }
        },
        {
            "product_info": {
                "plu": 4250088,
                "name": "Хлеб Рижский Хлеб Ремесленный чёрный заварной ржано-пшеничный, 300г",
                "property": "300 г"
            }
        },
        {
            "product_info": {
                "plu": 4380580,
                "name": "Батон Мосхлеб Нарезной нарезка 400г",
                "property": "400 г"
            }
        },
        {
            "product_info": {
                "plu": 4001716,
                "name": "Хлеб Самарский Пекарь Три злака со льном нарезка 350г",
                "property": "350 г"
            }
        },
        {
            "product_info": {
                "plu": 3404095,
                "name": "Хлеб Красная Цена Украинский 650г",
                "property": "650 г"
            }
        },
        {
            "product_info": {
                "plu": 3357340,
                "name": "Хлеб Щелковохлеб Рижский заварной нарезка 320г",
                "property": "320 г"
            }
        },
        {
            "product_info": {
                "plu": 4009100,
                "name": "Хлеб Рижский Хлеб Полбяной цельнозерновой 270г",
                "property": "270 г"
            }
        },
        {
            "product_info": {
                "plu": 4409919,
                "name": "Лаваш Выручай Армянский тонкий 270г",
                "property": "270 г"
            }
        },
        {
            "product_info": {
                "plu": 3219524,
                "name": "Хлеб Красная Цена Белый 380г",
                "property": "380 г"
            }
        },
        {
            "product_info": {
                "plu": 4354623,
                "name": "Хлеб ХЗ №22 Дарницкий формовой 700г",
                "property": "700 г"
            }
        },
        {
            "product_info": {
                "plu": 4338729,
                "name": "Хлеб Черемушки Дарницкий формовой нарезка 340г",
                "property": "340 г"
            }
        },
        {
            "product_info": {
                "plu": 4414403,
                "name": "Батон Булочный цех Классика нарезной 350г",
                "property": "350 г"
            }
        },
        {
            "product_info": {
                "plu": 3439816,
                "name": "Лепешки пшеничные Mission тортильи со злаками 250г",
                "property": "250 г"
            }
        },
        {
            "product_info": {
                "plu": 3684720,
                "name": "Хлеб Нижегородский хлеб Дарницкий формовой 700г",
                "property": "700 г"
            }
        },
        {
            "product_info": {
                "plu": 4315606,
                "name": "Лаваш Рижский Хлеб 150г",
                "property": "150 г"
            }
        },
        {
            "product_info": {
                "plu": 3679905,
                "name": "Хлеб Королевский Хлеб Столичный подовый нарезка 285г",
                "property": "285 г"
            }
        },
        {
            "product_info": {
                "plu": 4285055,
                "name": "Хлеб Рузский ХЗ Садко наливной 400г",
                "property": "400 г"
            }
        },
        {
            "product_info": {
                "plu": 4355964,
                "name": "Хлеб Дарницкий нарезка 160г",
                "property": "160 г"
            }
        },
        {
            "product_info": {
                "plu": 4050645,
                "name": "Хлебцы Бурже шведские с семенами 4х70г",
                "property": "280 г"
            }
        },
        {
            "product_info": {
                "plu": 3325471,
                "name": "Лаваш Черемушки Армянский тонкий 200г",
                "property": "200 г"
            }
        },
        {
            "product_info": {
                "plu": 3428312,
                "name": "Лаваш Рижский хлеб армянский 300г",
                "property": "300 г"
            }
        },
        {
            "product_info": {
                "plu": 4414402,
                "name": "Батон Булочный цех Зерновой на ржаном солоде нарезка 300г",
                "property": "300 г"
            }
        },
        {
            "product_info": {
                "plu": 2115832,
                "name": "Хлеб Серпуховхлеб Донской нарезка 350г",
                "property": "350 г"
            }
        },
        {
            "product_info": {
                "plu": 4403801,
                "name": "Батон МосХлеб Нарезной нарезка 195г",
                "property": "195 г"
            }
        },
        {
            "product_info": {
                "plu": 4252193,
                "name": "Хлеб Рижский Хлеб Ремесленный заварной из пшеничной муки 430г",
                "property": "430 г"
            }
        },
        {
            "product_info": {
                "plu": 4318511,
                "name": "Батон Маркет Зерновой нарезанный 300г",
                "property": "300 г"
            }
        },
        {
            "product_info": {
                "plu": 4409885,
                "name": "Лаваш Выручай Кавказский 280г",
                "property": "280 г"
            }
        },
        {
            "product_info": {
                "plu": 4218727,
                "name": "Лаваш Зерница Армянский тонкий 270г",
                "property": "270 г"
            }
        },
        {
            "product_info": {
                "plu": 3632218,
                "name": "Хлеб Эстонский 300г",
                "property": "300 г"
            }
        },
        {
            "product_info": {
                "plu": 4404303,
                "name": "Хлеб ЩелковоХлеб Ржевский нарезка 340г",
                "property": "340 г"
            }
        },
        {
            "product_info": {
                "plu": 4304557,
                "name": "Хлеб Толга Варницкий нарезанный 200г",
                "property": "200 г"
            }
        },
        {
            "product_info": {
                "plu": 4390373,
                "name": "Хлеб Пеко Тостовый пшеничный нарезка 250г",
                "property": "250 г"
            }
        },
        {
            "product_info": {
                "plu": 3642682,
                "name": "Хлеб Рузский ХЗ Паланга бездрожжевой заварной подовый нарезка 300г",
                "property": "300 г"
            }
        },
        {
            "product_info": {
                "plu": 4383471,
                "name": "Хлеб Коломенский Злаковый ржано-пшеничный с пророщенным зерном ржи нарезка 300г",
                "property": "300 г"
            }
        },
        {
            "product_info": {
                "plu": 4315649,
                "name": "Батончик Щелковохлеб Злаковое чудо нарезка 200г",
                "property": "200 г"
            }
        },
        {
            "product_info": {
                "plu": 4338725,
                "name": "Хлеб Рижский Хлеб Здоровый рецепт бездрожжевой заварной нарезка 300г",
                "property": "300 г"
            }
        },
        {
            "product_info": {
                "plu": 4288971,
                "name": "Хлеб Рижский Хлеб Ремесленный на пиве 250г",
                "property": "250 г"
            }
        },
        {
            "product_info": {
                "plu": 4252203,
                "name": "Чиабатта Рижский Хлеб цельнозерновая из смеси пшеничной муки 430г",
                "property": "250 г"
            }
        },
        {
            "product_info": {
                "plu": 4383472,
                "name": "Хлеб Коломенский Русский ржано-пшеничный нарезка 325г",
                "property": "325 г"
            }
        },
        {
            "product_info": {
                "plu": 4403799,
                "name": "Хлеб МосХлеб Дарницкий формовой нарезка 325г",
                "property": "325 г"
            }
        },
        {
            "product_info": {
                "plu": 4390372,
                "name": "Хлеб Пеко Тостовый пшеничный нарезка 520г",
                "property": "520 г"
            }
        },
        {
            "product_info": {
                "plu": 3431850,
                "name": "Хлеб Рижский Хлеб Станичный заварной подовый 250г",
                "property": "250 г"
            }
        },
        {
            "product_info": {
                "plu": 4371568,
                "name": "Хлеб Коломенский Двинский пшенично-ржаной нарезка 350г",
                "property": "350 г"
            }
        },
        {
            "product_info": {
                "plu": 4383470,
                "name": "Хлеб Коломенский Злаковый пшенично-ржаной с семенами подсолнечника и льна нарезка 300г",
                "property": "300 г"
            }
        },
        {
            "product_info": {
                "plu": 4390364,
                "name": "Хлеб Пеко Тостовый из смеси пшеничной и ржаной муки нарезка 550г",
                "property": "550 г"
            }
        },
        {
            "product_info": {
                "plu": 4403800,
                "name": "Хлеб Нива пшеничный 300г",
                "property": "300 г"
            }
        },
        {
            "product_info": {
                "plu": 4374772,
                "name": "Хлеб VQ формула белково-полбяной с изюмом и семечками нарезка 250г",
                "property": "250 г"
            }
        },
        {
            "product_info": {
                "plu": 4372913,
                "name": "Тортилья Tortillove пшенично-кукурузная 25см 240г",
                "property": "240 г"
            }
        },
        {
            "product_info": {
                "plu": 4285052,
                "name": "Хлебушек Рузский ХЗ Ремесленный злаковый с семенами льна и мака 330г",
                "property": "330 г"
            }
        },
        {
            "product_info": {
                "plu": 4382543,
                "name": "Лепешка Bikano Папад из муки бобовых острая с зирой 200г",
                "property": "200 г"
            }
        },
        {
            "product_info": {
                "plu": 4381814,
                "name": "Лепешка Bikano Папад из муки бобовых с черным перцем 200г",
                "property": "200 г"
            }
        },
        {
            "product_info": {
                "plu": 4351874,
                "name": "Хлеб Рижский Хлеб Знатный бездрожжевой заварной нарезка 220г",
                "property": "220 г"
            }
        },
        {
            "product_info": {
                "plu": 4329896,
                "name": "Хлебец Черемушки Полбяной с картофельными хлопьями нарезанный 300г",
                "property": "300 г"
            }
        },
        {
            "product_info": {
                "plu": 4317052,
                "name": "Булочка Маркет для гамбургера с кунжутом 3шт 165г",
                "property": "165 г"
            }
        },
        {
            "product_info": {
                "plu": 4085568,
                "name": "Кружка Atmosphere Black Swan фарфоровая 340мл",
                "property": "340 мл"
            }
        },
        {
            "product_info": {
                "plu": 4329895,
                "name": "Хлебец Черемушки Овсяный ароматный нарезанный 300г",
                "property": "300 г"
            }
        },
        {
            "product_info": {
                "plu": 4317073,
                "name": "Булочка Маркет для хот-дога 4шт 240г",
                "property": "240 г"
            }
        },
        {
            "product_info": {
                "plu": 4078875,
                "name": "Лаваш Рижский Хлеб тонкий 300г",
                "property": "300 г"
            }
        },
        {
            "product_info": {
                "plu": 2065126,
                "name": "Хлеб Коломенское ароматный 400г",
                "property": "400 г"
            }
        },
        {
            "product_info": {
                "plu": 4419904,
                "name": "Булочка Королевский Хлеб с отрубями 2х50г",
                "property": "100 г"
            }
        },
        {
            "product_info": {
                "plu": 4386492,
                "name": "Хлеб Haverland цельнозерновой из пшеницы-спельта-полбы 350г",
                "property": "350 г"
            }
        },
        {
            "product_info": {
                "plu": 4060707,
                "name": "Лаваш Рижский хлеб карри-чеснок из пшеничной муки 200г",
                "property": "200 г"
            }
        },
        {
            "product_info": {
                "plu": 4370712,
                "name": "Хлеб Нижегородский хлеб Буржуа нарезка 350г",
                "property": "350 г"
            }
        },
        {
            "product_info": {
                "plu": 4270857,
                "name": "Хлеб Национальные Традиции Матнакаш 400г",
                "property": "400 г"
            }
        },
        {
            "product_info": {
                "plu": 3442370,
                "name": "Лаваш Нижегородский Хлеб грузинский 300г",
                "property": "300 г"
            }
        },
        {
            "product_info": {
                "plu": 4218733,
                "name": "Лаваш Зерница Кавказский 280г",
                "property": "280 г"
            }
        },
        {
            "product_info": {
                "plu": 3600199,
                "name": "Батон Нарезной 400г",
                "property": "400 г"
            }
        },
        {
            "product_info": {
                "plu": 4380579,
                "name": "Ромашка Нижегородский хлеб 400г",
                "property": "400 г"
            }
        },
        {
            "product_info": {
                "plu": 4374771,
                "name": "Хлеб VQ формула Белково-полбяной многозерновой нарезка 250г",
                "property": "250 г"
            }
        }
    ]
}